{
  "node": {
    "60d2bd240379321eadae99dfefd453317fbb7163ab": {
      "workers": {
        "app/(home)/page": {
          "moduleId": "[project]/src/mydoc/.next-internal/server/app/(home)/page/actions.js { ACTIONS_MODULE0 => \"[project]/src/mydoc/lib/github.ts [app-rsc] (ecmascript)\" } [app-rsc] (server actions loader, ecmascript)",
          "async": false,
          "exportedName": "$$RSC_SERVER_ACTION_0",
          "filename": "src/mydoc/lib/github.ts"
        }
      },
      "layer": {
        "app/(home)/page": "rsc"
      },
      "exportedName": "$$RSC_SERVER_ACTION_0",
      "filename": "src/mydoc/lib/github.ts"
    }
  },
  "edge": {}
}